{
  "events": [
    {
      "title": "Derek's birthday",
      "date": "2026-04-05",
      "time": "All day",
      "end": "2026-04-06",
      "all_day": true,
      "location": null,
      "calendar": "Laure and Aaron "
    },
    {
      "title": "Ali birthday ",
      "date": "2026-04-05",
      "time": "All day",
      "end": "2026-04-06",
      "all_day": true,
      "location": null,
      "calendar": "Laure and Aaron "
    },
    {
      "title": "Supper?",
      "date": "2026-04-05",
      "time": "3:00 PM",
      "end": "2026-04-05T19:00:00",
      "all_day": false,
      "location": null,
      "calendar": "Laure and Aaron "
    },
    {
      "title": "Recycling day",
      "date": "2026-04-06",
      "time": "8:00 AM",
      "end": "2026-04-06T09:00:00",
      "all_day": false,
      "location": "249 Route 100\nHampton NB E5N 6Z3\nCanada",
      "calendar": "Laure and Aaron "
    },
    {
      "title": "Therapy",
      "date": "2026-04-06",
      "time": "7:00 PM",
      "end": "2026-04-06T20:00:00",
      "all_day": false,
      "location": null,
      "calendar": "Laure and Aaron "
    },
    {
      "title": "Garbage day",
      "date": "2026-04-07",
      "time": "8:00 AM",
      "end": "2026-04-07T09:00:00",
      "all_day": false,
      "location": "249 Route 100\nHampton NB E5N 6Z3\nCanada",
      "calendar": "Laure and Aaron "
    },
    {
      "title": "Tire and oil change",
      "date": "2026-04-07",
      "time": "8:30 AM",
      "end": "2026-04-07T09:30:00",
      "all_day": false,
      "location": null,
      "calendar": "Laure and Aaron "
    },
    {
      "title": "Massage Treatment with Jen Taylor",
      "date": "2026-04-07",
      "time": "6:30 PM",
      "end": "2026-04-07T19:30:00",
      "all_day": false,
      "location": "Jen Taylor Massage Therapy, 114 Logie Dr, Hampton, NB, E5N 5T2",
      "calendar": "Laure and Aaron "
    },
    {
      "title": "Pick hello fresh meals",
      "date": "2026-04-08",
      "time": "8:00 PM",
      "end": "2026-04-08T20:30:00",
      "all_day": false,
      "location": null,
      "calendar": "Laure and Aaron "
    },
    {
      "title": "Aaron physio",
      "date": "2026-04-09",
      "time": "11:00 AM",
      "end": "2026-04-09T12:00:00",
      "all_day": false,
      "location": "Station Street Health\n125 Station St, Saint John NB E2L 4X4, Canada",
      "calendar": "Laure and Aaron "
    },
    {
      "title": "Physio ",
      "date": "2026-04-09",
      "time": "5:00 PM",
      "end": "2026-04-09T18:00:00",
      "all_day": false,
      "location": null,
      "calendar": "Laure and Aaron "
    },
    {
      "title": "Laure in office ",
      "date": "2026-04-10",
      "time": "All day",
      "end": "2026-04-11",
      "all_day": true,
      "location": null,
      "calendar": "Laure and Aaron "
    },
    {
      "title": "Winnie swim \ud83c\udf0a",
      "date": "2026-04-11",
      "time": "9:30 AM",
      "end": "2026-04-11T10:00:00",
      "all_day": false,
      "location": "Ymca\n191 Churchill Blvd, Saint John NB E2K 3E2, Canada",
      "calendar": "Laure and Aaron "
    }
  ],
  "fetched_at": "2026-04-05T11:47:07.239338Z",
  "error": null
}